shinyobservable/__init__.py
shinyobservable/_context.py
shinyobservable/_core.py
shinyobservable/render.py
shinyobservable/srcjs/observable-bindings.js
shinyobservable/ui.py
shinyobservable-0.2.0.dist-info/METADATA
shinyobservable-0.2.0.dist-info/WHEEL
shinyobservable-0.2.0.dist-info/RECORD
