Metadata-Version: 2.1
Name: shinyobservable
Version: 0.2.0
Summary: Observable Notebooks and Cells in Shiny
License: MIT
Author: Stefan Kuethe
Author-email: stefan.kuethe@eoda.de
Requires-Python: >=3.9
Classifier: License :: OSI Approved :: MIT License
Classifier: Programming Language :: Python :: 3
Classifier: Programming Language :: Python :: 3.9
Classifier: Programming Language :: Python :: 3.10
Classifier: Programming Language :: Python :: 3.11
Requires-Dist: shiny (>=0.7.1,<0.8.0)
